koro/__init__.py
koro/py.typed
koro/slot/__init__.py
koro/slot/bin.py
koro/slot/file.py
koro/slot/save.py
koro/slot/xml.py
koro/stage/__init__.py
koro/stage/model.py
koro/stage/part.py
koro-2.0.3.dist-info/LICENSE
koro-2.0.3.dist-info/METADATA
koro-2.0.3.dist-info/WHEEL
koro-2.0.3.dist-info/top_level.txt
koro-2.0.3.dist-info/RECORD
