Metadata-Version: 2.2
Name: koro
Version: 2.0.3
Summary: Tools for manipulating levels made in Marble Saga: Kororinpa
Home-page: https://github.com/DigitalDetective47/koro
Author: DigitalDetective47
Author-email: ninji2701@gmail.com
Project-URL: Bug Tracker, https://github.com/DigitalDetective47/koro/issues
Project-URL: Documentation, https://github.com/DigitalDetective47/koro/wiki
Classifier: Development Status :: 5 - Production/Stable
Classifier: License :: OSI Approved :: The Unlicense (Unlicense)
Classifier: Operating System :: OS Independent
Classifier: Programming Language :: Python :: 3
Classifier: Programming Language :: Python :: 3 :: Only
Classifier: Programming Language :: Python :: 3.11
Classifier: Programming Language :: Python :: 3.12
Classifier: Programming Language :: Python :: 3.13
Classifier: Topic :: File Formats
Classifier: Topic :: Games/Entertainment
Classifier: Typing :: Typed
Requires-Python: >=3.11
License-File: LICENSE
